{
  "site": "yggtorrent",
  "name": "YGGtorrent",
  "language": "fr-FR",
  "encoding": "UTF-8",
  "links": ["https://yggtorrent.is"],
  "caps": {
    "modes": { "search": ["q"], "tv-search": ["q", "season", "ep"] },
    "categorymappings": [
      { "id": "2139", "cat": "Other" },
      { "id": "2140", "cat": "Other" },
      { "id": "2141", "cat": "Other" },
      { "id": "2142", "cat": "Other" },
      { "id": "2143", "cat": "Other" },
      { "id": "2144", "cat": "PC" },
      { "id": "2145", "cat": "Other" },
      { "id": "2147", "cat": "Audio" },
      { "id": "2148", "cat": "Audio" },
      { "id": "2149", "cat": "Audio" },
      { "id": "2150", "cat": "Audio" },
      { "id": "2151", "cat": "Audio/Audiobook" },
      { "id": "2152", "cat": "Books/Comics" },
      { "id": "2153", "cat": "Books/Comics" },
      { "id": "2154", "cat": "Books/Ebook" },
      { "id": "2155", "cat": "Books" },
      { "id": "2156", "cat": "Books/Magazines" },
      { "id": "2157", "cat": "Other/Misc" },
      { "id": "2158", "cat": "Other/Misc" },
      { "id": "2159", "cat": "PC/Games" },
      { "id": "2160", "cat": "PC/Games" },
      { "id": "2161", "cat": "PC/Games" },
      { "id": "2162", "cat": "Console" },
      { "id": "2163", "cat": "Console" },
      { "id": "2164", "cat": "Console" },
      { "id": "2165", "cat": "PC/Phone-Other" },
      { "id": "2166", "cat": "PC/Games" },
      { "id": "2167", "cat": "Other" },
      { "id": "2168", "cat": "Other/Misc" },
      { "id": "2169", "cat": "Other/Misc" },
      { "id": "2170", "cat": "Other/Misc" },
      { "id": "2171", "cat": "PC" },
      { "id": "2172", "cat": "PC/Mac" },
      { "id": "2173", "cat": "PC" },
      { "id": "2174", "cat": "PC/Phone-Other" },
      { "id": "2175", "cat": "PC/Phone-Other" },
      { "id": "2176", "cat": "PC" },
      { "id": "2177", "cat": "PC" },
      { "id": "2178", "cat": "Movies" },
      { "id": "2179", "cat": "TV/Anime" },
      { "id": "2180", "cat": "Audio/Video" },
      { "id": "2181", "cat": "TV/Documentary" },
      { "id": "2182", "cat": "TV" },
      { "id": "2183", "cat": "Movies" },
      { "id": "2184", "cat": "TV" },
      { "id": "2185", "cat": "Movies/Other" },
      { "id": "2186", "cat": "TV/Sport" },
      { "id": "2187", "cat": "Audio/Video" },
      { "id": "2188", "cat": "XXX" },
      { "id": "2189", "cat": "XXX" },
      { "id": "2190", "cat": "XXX/Other" },
      { "id": "2191", "cat": "XXX/Imageset" },
      { "id": "filmvidéo/animation", "cat": "Movies" },
      { "id": "filmvidéo/animation-série", "cat": "TV/Anime" },
      { "id": "filmvidéo/concert", "cat": "Audio/Video" },
      { "id": "filmvidéo/documentaire", "cat": "TV/Documentary" },
      { "id": "filmvidéo/emission-tv", "cat": "TV" },
      { "id": "filmvidéo/film", "cat": "Movies" },
      { "id": "filmvidéo/série-tv", "cat": "TV" },
      { "id": "filmvidéo/spectacle", "cat": "Movies/Other" },
      { "id": "filmvidéo/sport", "cat": "TV/Sport" },
      { "id": "filmvidéo/vidéo-clips", "cat": "Audio/Video" },
      { "id": "audio/karaoké", "cat": "Audio" },
      { "id": "audio/musique", "cat": "Audio" },
      { "id": "audio/podcast-radio", "cat": "Audio" },
      { "id": "audio/samples", "cat": "Audio" },
      { "id": "application/autre", "cat": "PC" },
      { "id": "application/formation", "cat": "PC" },
      { "id": "application/linux", "cat": "PC" },
      { "id": "application/macos", "cat": "PC/Mac" },
      { "id": "application/smartphone", "cat": "PC/Phone-Other" },
      { "id": "application/tablette", "cat": "PC/Phone-Other" },
      { "id": "application/windows", "cat": "PC" },
      { "id": "jeu-vidéo/autre", "cat": "Other" },
      { "id": "jeu-vidéo/linux", "cat": "PC/Games" },
      { "id": "jeu-vidéo/macos", "cat": "PC/Games" },
      { "id": "jeu-vidéo/microsoft", "cat": "Console" },
      { "id": "jeu-vidéo/nintendo", "cat": "Console" },
      { "id": "jeu-vidéo/smartphone", "cat": "PC/Phone-Other" },
      { "id": "jeu-vidéo/sony", "cat": "Console" },
      { "id": "jeu-vidéo/tablette", "cat": "PC/Games" },
      { "id": "jeu-vidéo/windows", "cat": "PC/Games" },
      { "id": "ebook/audio", "cat": "Audio/Audiobook" },
      { "id": "ebook/bds", "cat": "Books/Comics" },
      { "id": "ebook/comics", "cat": "Books/Comics" },
      { "id": "ebook/livres", "cat": "Books/Ebook" },
      { "id": "ebook/mangas", "cat": "Books" },
      { "id": "ebook/presse", "cat": "Books/Magazines" },
      { "id": "emulation/emulateurs", "cat": "Other/Misc" },
      { "id": "emulation/roms", "cat": "Other/Misc" },
      { "id": "gps/applications", "cat": "Other/Misc" },
      { "id": "gps/cartes", "cat": "Other/Misc" },
      { "id": "gps/divers", "cat": "Other/Misc" },
      { "id": "xxx/films", "cat": "XXX" },
      { "id": "xxx/hentai", "cat": "XXX/Other" },
      { "id": "xxx/images", "cat": "XXX/Imageset" }
    ]
  },
  "settings": [
    {
      "name": "username",
      "type": "text",
      "label": "Username (email or username)"
    },
    { "name": "password", "type": "password", "label": "Password" }
  ],
  "login": {
    "path": "/user/login",
    "method": "post",
    "inputs": {
      "id": "{{ .Config.username }}",
      "pass": "{{ .Config.password }}",
      "submit": ""
    },
    "headers": {
      "[:authority]": "yggtorrent.com",
      "[:method]": "post",
      "[:path]": "/",
      "[:scheme]": "https"
    },
    "error": [
      {
        "selector": "div#top_panel > div > ul > li:nth-child(1) > a.text:contains(\"S'identifier\")"
      }
    ],
    "test": { "path": "/", "selector": "a[href$=\"/user/logout\"]" }
  },
  "search": {
    "path": "/engine/search?name={{ .Keywords}}&do=search",
    "rows": { "selector": "section#\\#torrents > div > table > tbody > tr" },
    "fields": {
      "date": {
        "selector": "td:nth-child(5)",
        "filters": [
          { "name": "regexp", "args": "^[0-9]+ (.+)$" },
          { "name": "replace", "args": [" jours", " days"] },
          { "name": "replace", "args": [" jour", " day"] },
          { "name": "replace", "args": [" heures", " hours"] },
          { "name": "replace", "args": [" heure", " hour"] },
          { "name": "replace", "args": [" semaines", " weeks"] },
          { "name": "replace", "args": [" semaine", " week"] },
          { "name": "replace", "args": [" mois", " month"] },
          { "name": "replace", "args": [" ans", " years"] },
          { "name": "replace", "args": [" an", " year"] },
          { "name": "append", "args": " ago" }
        ]
      },
      "title": { "selector": "td:nth-child(2) > a" },
      "details": { "selector": "td:nth-child(2) > a", "attribute": "href" },
      "category": { "selector": "td:nth-child(1) > div.hidden:nth-child(1)" },
      "comments": {
        "optional": true,
        "selector": "td:nth-child(2) > a",
        "attribute": "href"
      },
      "download": {
        "selector": "td:nth-child(2) > a",
        "attribute": "href",
        "filters": [
          { "name": "regexp", "args": ".+/([^/]+)" },
          { "name": "regexp", "args": "^([0-9]+)-.*" },
          { "name": "prepend", "args": "/engine/download_torrent?id=" }
        ]
      },
      "size": {
        "selector": "td:nth-child(6)",
        "filters": [
          { "name": "replace", "args": ["Ko", "kib"] },
          { "name": "replace", "args": ["Mo", "mib"] },
          { "name": "replace", "args": ["Go", "gib"] },
          { "name": "replace", "args": ["To", "tib"] }
        ]
      },
      "seeders": { "selector": "td:nth-child(8)" },
      "leechers": { "selector": "td:nth-child(9)" },
      "downloadvolumefactor": { "text": "1" },
      "uploadvolumefactor": { "text": "1" }
    }
  },
  "source": "cardigann"
}
